freshbooks/VERSION
freshbooks/__init__.py
freshbooks/client.py
freshbooks/errors.py
freshbooks/models.py
freshbooks/py.typed
freshbooks/api/__init__.py
freshbooks/api/accounting.py
freshbooks/api/accounting_business.py
freshbooks/api/auth.py
freshbooks/api/comments.py
freshbooks/api/events.py
freshbooks/api/payments.py
freshbooks/api/projects.py
freshbooks/api/resource.py
freshbooks/api/timetracking.py
freshbooks/api/uploads.py
freshbooks/builders/__init__.py
freshbooks/builders/filter.py
freshbooks/builders/includes.py
freshbooks/builders/paginator.py
freshbooks/builders/sort.py
freshbooks_sdk-1.3.0.dist-info/LICENSE
freshbooks_sdk-1.3.0.dist-info/METADATA
freshbooks_sdk-1.3.0.dist-info/WHEEL
freshbooks_sdk-1.3.0.dist-info/top_level.txt
freshbooks_sdk-1.3.0.dist-info/RECORD
