Metadata-Version: 2.1
Name: freshbooks-sdk
Version: 1.3.0
Summary: API client for FreshBooks
Home-page: https://github.com/amcintosh/freshbooks-python-sdk
Download-URL: https://github.com/amcintosh/freshbooks-python-sdk/archive/release/1.3.0.tar.gz
Author: Andrew McIntosh
Author-email: andrew@amcintosh.net
License: MIT
Keywords: FreshBooks
Classifier: Development Status :: 4 - Beta
Classifier: Intended Audience :: Developers
Classifier: License :: OSI Approved :: MIT License
Classifier: Natural Language :: English
Classifier: Programming Language :: Python
Classifier: Programming Language :: Python :: 3
Classifier: Programming Language :: Python :: 3 :: Only
Classifier: Programming Language :: Python :: 3.8
Classifier: Programming Language :: Python :: 3.9
Classifier: Programming Language :: Python :: 3.10
Classifier: Programming Language :: Python :: 3.11
Classifier: Programming Language :: Python :: 3.12
Classifier: Programming Language :: Python :: 3.13
License-File: LICENSE
Requires-Dist: urllib3>=1.26
Requires-Dist: requests
Requires-Dist: backports.zoneinfo; python_version < "3.9"
